elevator-chisel/generated/ElevatorController.sv
// Generated by CIRCT firtool-1.62.0
// Standard header to adapt well known macros for register randomization.
`ifndef RANDOMIZE
  `ifdef RANDOMIZE_REG_INIT
    `define RANDOMIZE
  `endif // RANDOMIZE_REG_INIT
`endif // not def RANDOMIZE

// RANDOM may be set to an expression that produces a 32-bit random unsigned value.
`ifndef RANDOM
  `define RANDOM $random
`endif // not def RANDOM

// Users can define INIT_RANDOM as general code that gets injected into the
// initializer block for modules with registers.
`ifndef INIT_RANDOM
  `define INIT_RANDOM
`endif // not def INIT_RANDOM

// If using random initialization, you can also define RANDOMIZE_DELAY to
// customize the delay used, otherwise 0.002 is used.
`ifndef RANDOMIZE_DELAY
  `define RANDOMIZE_DELAY 0.002
`endif // not def RANDOMIZE_DELAY

// Define INIT_RANDOM_PROLOG_ for use in our modules below.
`ifndef INIT_RANDOM_PROLOG_
  `ifdef RANDOMIZE
    `ifdef VERILATOR
      `define INIT_RANDOM_PROLOG_ `INIT_RANDOM
    `else  // VERILATOR
      `define INIT_RANDOM_PROLOG_ `INIT_RANDOM #`RANDOMIZE_DELAY begin end
    `endif // VERILATOR
  `else  // RANDOMIZE
    `define INIT_RANDOM_PROLOG_
  `endif // RANDOMIZE
`endif // not def INIT_RANDOM_PROLOG_

// Include register initializers in init blocks unless synthesis is set
`ifndef SYNTHESIS
  `ifndef ENABLE_INITIAL_REG_
    `define ENABLE_INITIAL_REG_
  `endif // not def ENABLE_INITIAL_REG_
`endif // not def SYNTHESIS

// Include rmemory initializers in init blocks unless synthesis is set
`ifndef SYNTHESIS
  `ifndef ENABLE_INITIAL_MEM_
    `define ENABLE_INITIAL_MEM_
  `endif // not def ENABLE_INITIAL_MEM_
`endif // not def SYNTHESIS

module ElevatorController(	// src/main/scala/elevator/ElevatorController.scala:6:7
  input        clock,	// src/main/scala/elevator/ElevatorController.scala:6:7
               reset,	// src/main/scala/elevator/ElevatorController.scala:6:7
  input  [3:0] io_floorRequest,	// src/main/scala/elevator/ElevatorController.scala:7:14
               io_currentFloorSensor,	// src/main/scala/elevator/ElevatorController.scala:7:14
  input        io_doorSensor,	// src/main/scala/elevator/ElevatorController.scala:7:14
               io_emergency,	// src/main/scala/elevator/ElevatorController.scala:7:14
               io_overload,	// src/main/scala/elevator/ElevatorController.scala:7:14
  output       io_motorUp,	// src/main/scala/elevator/ElevatorController.scala:7:14
               io_motorDown,	// src/main/scala/elevator/ElevatorController.scala:7:14
               io_doorOpen,	// src/main/scala/elevator/ElevatorController.scala:7:14
               io_doorClose,	// src/main/scala/elevator/ElevatorController.scala:7:14
  output [2:0] io_currentState,	// src/main/scala/elevator/ElevatorController.scala:7:14
  output [1:0] io_currentFloor	// src/main/scala/elevator/ElevatorController.scala:7:14
);

  reg [2:0] state;	// src/main/scala/elevator/ElevatorController.scala:26:22
  reg [1:0] currentFloor;	// src/main/scala/elevator/ElevatorController.scala:27:29
  reg [1:0] targetFloor;	// src/main/scala/elevator/ElevatorController.scala:28:28
  reg       requestQueue_0;	// src/main/scala/elevator/ElevatorController.scala:29:29
  reg       requestQueue_1;	// src/main/scala/elevator/ElevatorController.scala:29:29
  reg       requestQueue_2;	// src/main/scala/elevator/ElevatorController.scala:29:29
  reg       requestQueue_3;	// src/main/scala/elevator/ElevatorController.scala:29:29
  always @(posedge clock) begin	// src/main/scala/elevator/ElevatorController.scala:6:7
    if (reset) begin	// src/main/scala/elevator/ElevatorController.scala:6:7
      state <= 3'h0;	// src/main/scala/elevator/ElevatorController.scala:26:22
      currentFloor <= 2'h0;	// src/main/scala/elevator/ElevatorController.scala:27:29
      targetFloor <= 2'h0;	// src/main/scala/elevator/ElevatorController.scala:27:29, :28:28
      requestQueue_0 <= 1'h0;	// src/main/scala/elevator/ElevatorController.scala:6:7, :29:29
      requestQueue_1 <= 1'h0;	// src/main/scala/elevator/ElevatorController.scala:6:7, :29:29
      requestQueue_2 <= 1'h0;	// src/main/scala/elevator/ElevatorController.scala:6:7, :29:29
      requestQueue_3 <= 1'h0;	// src/main/scala/elevator/ElevatorController.scala:6:7, :29:29
    end
    else begin	// src/main/scala/elevator/ElevatorController.scala:6:7
      automatic logic       _GEN;	// src/main/scala/elevator/ElevatorController.scala:29:29, :34:30, :35:23
      automatic logic       _GEN_0;	// src/main/scala/elevator/ElevatorController.scala:29:29, :34:30, :35:23
      automatic logic       _GEN_1;	// src/main/scala/elevator/ElevatorController.scala:29:29, :34:30, :35:23
      automatic logic       _GEN_2;	// src/main/scala/elevator/ElevatorController.scala:29:29, :34:30, :35:23
      automatic logic       _GEN_3;	// src/main/scala/elevator/ElevatorController.scala:49:19
      automatic logic [3:0] _GEN_4;	// src/main/scala/elevator/ElevatorController.scala:51:27
      automatic logic       _hasUpperRequest_T_2;	// src/main/scala/elevator/ElevatorController.scala:53:25
      automatic logic       _hasUpperRequest_T_6;	// src/main/scala/elevator/ElevatorController.scala:53:25
      automatic logic       hasUpperRequest;	// src/main/scala/elevator/ElevatorController.scala:54:22
      automatic logic       hasLowerRequest;	// src/main/scala/elevator/ElevatorController.scala:58:22
      automatic logic [3:0] _GEN_5;	// src/main/scala/elevator/ElevatorController.scala:60:44
      automatic logic       _GEN_6;	// src/main/scala/elevator/ElevatorController.scala:60:44
      automatic logic       _GEN_7;	// src/main/scala/elevator/ElevatorController.scala:63:40
      automatic logic       _GEN_8;	// src/main/scala/elevator/ElevatorController.scala:34:30, :60:44, :63:40
      automatic logic       _GEN_9;	// src/main/scala/elevator/ElevatorController.scala:63:40
      automatic logic       _GEN_10;	// src/main/scala/elevator/ElevatorController.scala:34:30, :60:44, :63:40
      automatic logic       _GEN_11;	// src/main/scala/elevator/ElevatorController.scala:63:40
      automatic logic       _GEN_12;	// src/main/scala/elevator/ElevatorController.scala:34:30, :60:44, :63:40
      automatic logic       _GEN_13;	// src/main/scala/elevator/ElevatorController.scala:34:30, :60:44, :63:40
      automatic logic       _GEN_14;	// src/main/scala/elevator/ElevatorController.scala:83:27
      automatic logic       _GEN_15;	// src/main/scala/elevator/ElevatorController.scala:49:19, :83:44
      _GEN = io_floorRequest[0] | requestQueue_0;	// src/main/scala/elevator/ElevatorController.scala:29:29, :34:{25,30}, :35:23
      _GEN_0 = io_floorRequest[1] | requestQueue_1;	// src/main/scala/elevator/ElevatorController.scala:29:29, :34:{25,30}, :35:23
      _GEN_1 = io_floorRequest[2] | requestQueue_2;	// src/main/scala/elevator/ElevatorController.scala:29:29, :34:{25,30}, :35:23
      _GEN_2 = io_floorRequest[3] | requestQueue_3;	// src/main/scala/elevator/ElevatorController.scala:29:29, :34:{25,30}, :35:23
      _GEN_3 = state == 3'h0;	// src/main/scala/elevator/ElevatorController.scala:26:22, :49:19
      _GEN_4 = {requestQueue_3, requestQueue_2, requestQueue_1, requestQueue_0};	// src/main/scala/elevator/ElevatorController.scala:29:29, :51:27
      _hasUpperRequest_T_2 = currentFloor == 2'h0;	// src/main/scala/elevator/ElevatorController.scala:27:29, :53:25
      _hasUpperRequest_T_6 = currentFloor != 2'h3;	// src/main/scala/elevator/ElevatorController.scala:27:29, :41:20, :53:25
      hasUpperRequest =
        requestQueue_1 & _hasUpperRequest_T_2 | requestQueue_2 & ~(currentFloor[1])
        | requestQueue_3 & _hasUpperRequest_T_6;	// src/main/scala/elevator/ElevatorController.scala:27:29, :29:29, :53:{17,25}, :54:22
      hasLowerRequest =
        requestQueue_0 & (|currentFloor) | requestQueue_1 & currentFloor[1]
        | requestQueue_2 & (&currentFloor);	// src/main/scala/elevator/ElevatorController.scala:27:29, :29:29, :57:{17,25}, :58:22
      _GEN_5 = {{requestQueue_3}, {requestQueue_2}, {requestQueue_1}, {requestQueue_0}};	// src/main/scala/elevator/ElevatorController.scala:29:29, :60:44
      _GEN_6 = _GEN_5[currentFloor];	// src/main/scala/elevator/ElevatorController.scala:27:29, :60:44
      _GEN_7 = currentFloor == 2'h0;	// src/main/scala/elevator/ElevatorController.scala:27:29, :63:40
      _GEN_8 = _GEN_6 & _GEN_7;	// src/main/scala/elevator/ElevatorController.scala:34:30, :60:44, :63:40
      _GEN_9 = currentFloor == 2'h1;	// src/main/scala/elevator/ElevatorController.scala:27:29, :63:40
      _GEN_10 = _GEN_6 & _GEN_9;	// src/main/scala/elevator/ElevatorController.scala:34:30, :60:44, :63:40
      _GEN_11 = currentFloor == 2'h2;	// src/main/scala/elevator/ElevatorController.scala:27:29, :41:20, :63:40
      _GEN_12 = _GEN_6 & _GEN_11;	// src/main/scala/elevator/ElevatorController.scala:34:30, :60:44, :63:40
      _GEN_13 = _GEN_6 & (&currentFloor);	// src/main/scala/elevator/ElevatorController.scala:27:29, :34:30, :60:44, :63:40
      _GEN_14 = currentFloor == targetFloor;	// src/main/scala/elevator/ElevatorController.scala:27:29, :28:28, :83:27
      _GEN_15 = state == 3'h1 | state == 3'h2;	// src/main/scala/elevator/ElevatorController.scala:26:22, :49:19, :70:19, :77:19, :83:44
      if (io_emergency)	// src/main/scala/elevator/ElevatorController.scala:7:14
        state <= 3'h6;	// src/main/scala/elevator/ElevatorController.scala:26:22, :46:11
      else begin	// src/main/scala/elevator/ElevatorController.scala:7:14
        automatic logic [2:0]      _GEN_16;	// src/main/scala/elevator/ElevatorController.scala:26:22, :83:44, :84:17, :86:49, :87:17
        automatic logic [2:0]      _GEN_17;	// src/main/scala/elevator/ElevatorController.scala:26:22, :49:19, :123:47, :124:17
        automatic logic [7:0][2:0] _GEN_18;	// src/main/scala/elevator/ElevatorController.scala:49:19, :51:43, :83:44, :103:29, :111:41, :117:30
        _GEN_16 = _GEN_14 | _GEN_6 ? 3'h3 : state;	// src/main/scala/elevator/ElevatorController.scala:26:22, :60:44, :62:19, :83:{27,44}, :84:17, :86:49, :87:17
        _GEN_17 = state == 3'h6 & ~io_emergency & ~io_doorSensor ? 3'h0 : state;	// src/main/scala/elevator/ElevatorController.scala:26:22, :46:11, :49:19, :117:14, :123:{14,47}, :124:17
        _GEN_18 =
          {{_GEN_17},
           {_GEN_17},
           {io_doorSensor ? state : 3'h0},
           {state},
           {io_doorSensor ? 3'h4 : state},
           {_GEN_16},
           {_GEN_16},
           {(|_GEN_4)
              ? (_GEN_6 ? 3'h3 : hasUpperRequest ? 3'h1 : hasLowerRequest ? 3'h2 : state)
              : state}};	// src/main/scala/elevator/ElevatorController.scala:26:22, :49:19, :51:{27,34,43}, :54:22, :58:22, :60:44, :62:19, :64:40, :70:19, :71:40, :77:19, :83:44, :84:17, :86:49, :87:17, :103:29, :104:17, :111:41, :117:30, :118:17, :123:47, :124:17
        state <= _GEN_18[state];	// src/main/scala/elevator/ElevatorController.scala:26:22, :49:19, :51:43, :83:44, :103:29, :111:41, :117:30
      end
      if (io_currentFloorSensor[3])	// src/main/scala/elevator/ElevatorController.scala:40:31
        currentFloor <= 2'h3;	// src/main/scala/elevator/ElevatorController.scala:27:29, :41:20
      else if (io_currentFloorSensor[2])	// src/main/scala/elevator/ElevatorController.scala:40:31
        currentFloor <= 2'h2;	// src/main/scala/elevator/ElevatorController.scala:27:29, :41:20
      else if (io_currentFloorSensor[1])	// src/main/scala/elevator/ElevatorController.scala:40:31
        currentFloor <= 2'h1;	// src/main/scala/elevator/ElevatorController.scala:27:29, :63:40
      else if (io_currentFloorSensor[0])	// src/main/scala/elevator/ElevatorController.scala:40:31
        currentFloor <= 2'h0;	// src/main/scala/elevator/ElevatorController.scala:27:29
      if (io_emergency | ~(_GEN_3 & (|_GEN_4))) begin	// src/main/scala/elevator/ElevatorController.scala:28:28, :45:22, :49:19, :51:{27,34,43}, :60:44
      end
      else if (_GEN_6)	// src/main/scala/elevator/ElevatorController.scala:60:44
        targetFloor <= currentFloor;	// src/main/scala/elevator/ElevatorController.scala:27:29, :28:28
      else if (hasUpperRequest) begin	// src/main/scala/elevator/ElevatorController.scala:54:22
        if (requestQueue_1 & _hasUpperRequest_T_2)	// src/main/scala/elevator/ElevatorController.scala:29:29, :53:25, :66:36
          targetFloor <= 2'h1;	// src/main/scala/elevator/ElevatorController.scala:28:28, :63:40
        else if (requestQueue_2 & ~(currentFloor[1]))	// src/main/scala/elevator/ElevatorController.scala:27:29, :29:29, :53:25, :66:36
          targetFloor <= 2'h2;	// src/main/scala/elevator/ElevatorController.scala:28:28, :41:20
        else if (requestQueue_3 & _hasUpperRequest_T_6)	// src/main/scala/elevator/ElevatorController.scala:29:29, :53:25, :66:36
          targetFloor <= 2'h3;	// src/main/scala/elevator/ElevatorController.scala:28:28, :41:20
      end
      else if (hasLowerRequest) begin	// src/main/scala/elevator/ElevatorController.scala:58:22
        if (requestQueue_2 & (&currentFloor))	// src/main/scala/elevator/ElevatorController.scala:27:29, :29:29, :57:25, :73:36
          targetFloor <= 2'h2;	// src/main/scala/elevator/ElevatorController.scala:28:28, :41:20
        else if (requestQueue_1 & currentFloor[1])	// src/main/scala/elevator/ElevatorController.scala:27:29, :29:29, :57:25, :73:36
          targetFloor <= 2'h1;	// src/main/scala/elevator/ElevatorController.scala:28:28, :63:40
        else if (requestQueue_0 & (|currentFloor))	// src/main/scala/elevator/ElevatorController.scala:27:29, :29:29, :57:25, :73:36
          targetFloor <= 2'h0;	// src/main/scala/elevator/ElevatorController.scala:27:29, :28:28
      end
      requestQueue_0 <=
        ~io_emergency
        & (_GEN_3
             ? ~((|_GEN_4) & _GEN_8) & _GEN
             : _GEN_15 ? (_GEN_14 ? ~_GEN_7 & _GEN : ~_GEN_8 & _GEN) : _GEN);	// src/main/scala/elevator/ElevatorController.scala:29:29, :34:30, :35:23, :45:22, :47:28, :49:19, :51:{27,34,43}, :60:44, :63:40, :83:{27,44}, :85:38, :86:49, :88:38
      requestQueue_1 <=
        ~io_emergency
        & (_GEN_3
             ? ~((|_GEN_4) & _GEN_10) & _GEN_0
             : _GEN_15 ? (_GEN_14 ? ~_GEN_9 & _GEN_0 : ~_GEN_10 & _GEN_0) : _GEN_0);	// src/main/scala/elevator/ElevatorController.scala:29:29, :34:30, :35:23, :45:22, :47:28, :49:19, :51:{27,34,43}, :60:44, :63:40, :83:{27,44}, :85:38, :86:49, :88:38
      requestQueue_2 <=
        ~io_emergency
        & (_GEN_3
             ? ~((|_GEN_4) & _GEN_12) & _GEN_1
             : _GEN_15 ? (_GEN_14 ? ~_GEN_11 & _GEN_1 : ~_GEN_12 & _GEN_1) : _GEN_1);	// src/main/scala/elevator/ElevatorController.scala:29:29, :34:30, :35:23, :45:22, :47:28, :49:19, :51:{27,34,43}, :60:44, :63:40, :83:{27,44}, :85:38, :86:49, :88:38
      requestQueue_3 <=
        ~io_emergency
        & (_GEN_3
             ? ~((|_GEN_4) & _GEN_13) & _GEN_2
             : _GEN_15
                 ? (_GEN_14 ? ~(&currentFloor) & _GEN_2 : ~_GEN_13 & _GEN_2)
                 : _GEN_2);	// src/main/scala/elevator/ElevatorController.scala:27:29, :29:29, :34:30, :35:23, :45:22, :47:28, :49:19, :51:{27,34,43}, :60:44, :63:40, :83:{27,44}, :85:38, :86:49, :88:38
    end
  end // always @(posedge)
  `ifdef ENABLE_INITIAL_REG_	// src/main/scala/elevator/ElevatorController.scala:6:7
    `ifdef FIRRTL_BEFORE_INITIAL	// src/main/scala/elevator/ElevatorController.scala:6:7
      `FIRRTL_BEFORE_INITIAL	// src/main/scala/elevator/ElevatorController.scala:6:7
    `endif // FIRRTL_BEFORE_INITIAL
    initial begin	// src/main/scala/elevator/ElevatorController.scala:6:7
      automatic logic [31:0] _RANDOM[0:0];	// src/main/scala/elevator/ElevatorController.scala:6:7
      `ifdef INIT_RANDOM_PROLOG_	// src/main/scala/elevator/ElevatorController.scala:6:7
        `INIT_RANDOM_PROLOG_	// src/main/scala/elevator/ElevatorController.scala:6:7
      `endif // INIT_RANDOM_PROLOG_
      `ifdef RANDOMIZE_REG_INIT	// src/main/scala/elevator/ElevatorController.scala:6:7
        _RANDOM[/*Zero width*/ 1'b0] = `RANDOM;	// src/main/scala/elevator/ElevatorController.scala:6:7
        state = _RANDOM[/*Zero width*/ 1'b0][2:0];	// src/main/scala/elevator/ElevatorController.scala:6:7, :26:22
        currentFloor = _RANDOM[/*Zero width*/ 1'b0][4:3];	// src/main/scala/elevator/ElevatorController.scala:6:7, :26:22, :27:29
        targetFloor = _RANDOM[/*Zero width*/ 1'b0][6:5];	// src/main/scala/elevator/ElevatorController.scala:6:7, :26:22, :28:28
        requestQueue_0 = _RANDOM[/*Zero width*/ 1'b0][7];	// src/main/scala/elevator/ElevatorController.scala:6:7, :26:22, :29:29
        requestQueue_1 = _RANDOM[/*Zero width*/ 1'b0][8];	// src/main/scala/elevator/ElevatorController.scala:6:7, :26:22, :29:29
        requestQueue_2 = _RANDOM[/*Zero width*/ 1'b0][9];	// src/main/scala/elevator/ElevatorController.scala:6:7, :26:22, :29:29
        requestQueue_3 = _RANDOM[/*Zero width*/ 1'b0][10];	// src/main/scala/elevator/ElevatorController.scala:6:7, :26:22, :29:29
      `endif // RANDOMIZE_REG_INIT
    end // initial
    `ifdef FIRRTL_AFTER_INITIAL	// src/main/scala/elevator/ElevatorController.scala:6:7
      `FIRRTL_AFTER_INITIAL	// src/main/scala/elevator/ElevatorController.scala:6:7
    `endif // FIRRTL_AFTER_INITIAL
  `endif // ENABLE_INITIAL_REG_
  assign io_motorUp = state == 3'h1;	// src/main/scala/elevator/ElevatorController.scala:6:7, :26:22, :70:19, :130:23
  assign io_motorDown = state == 3'h2;	// src/main/scala/elevator/ElevatorController.scala:6:7, :26:22, :77:19, :131:25
  assign io_doorOpen = state == 3'h3 | state == 3'h4 | state == 3'h6;	// src/main/scala/elevator/ElevatorController.scala:6:7, :26:22, :46:11, :62:19, :104:17, :132:{24,55,78,87}
  assign io_doorClose = state == 3'h5;	// src/main/scala/elevator/ElevatorController.scala:6:7, :26:22, :112:17, :133:25
  assign io_currentState = state;	// src/main/scala/elevator/ElevatorController.scala:6:7, :26:22
  assign io_currentFloor = currentFloor;	// src/main/scala/elevator/ElevatorController.scala:6:7, :27:29
endmodule

elevator-chisel/elevator_verilator.vcd
$version Generated by VerilatedVcd $end
$timescale 1ps $end
 $scope module TOP $end
  $var wire 1 , clock $end
  $var wire 1 - reset $end
  $var wire 4 . io_floorRequest [3:0] $end
  $var wire 4 / io_currentFloorSensor [3:0] $end
  $var wire 1 0 io_doorSensor $end
  $var wire 1 1 io_emergency $end
  $var wire 1 2 io_overload $end
  $var wire 1 3 io_motorUp $end
  $var wire 1 4 io_motorDown $end
  $var wire 1 5 io_doorOpen $end
  $var wire 1 6 io_doorClose $end
  $var wire 3 7 io_currentState [2:0] $end
  $var wire 2 8 io_currentFloor [1:0] $end
  $scope module ElevatorController $end
   $var wire 1 , clock $end
   $var wire 1 - reset $end
   $var wire 4 . io_floorRequest [3:0] $end
   $var wire 4 / io_currentFloorSensor [3:0] $end
   $var wire 1 0 io_doorSensor $end
   $var wire 1 1 io_emergency $end
   $var wire 1 2 io_overload $end
   $var wire 1 3 io_motorUp $end
   $var wire 1 4 io_motorDown $end
   $var wire 1 5 io_doorOpen $end
   $var wire 1 6 io_doorClose $end
   $var wire 3 7 io_currentState [2:0] $end
   $var wire 2 8 io_currentFloor [1:0] $end
   $var wire 3 # state [2:0] $end
   $var wire 2 $ currentFloor [1:0] $end
   $var wire 2 % targetFloor [1:0] $end
   $var wire 1 & requestQueue_0 $end
   $var wire 1 ' requestQueue_1 $end
   $var wire 1 ( requestQueue_2 $end
   $var wire 1 ) requestQueue_3 $end
   $scope module unnamedblk1 $end
    $var wire 1 * hasUpperRequest $end
    $var wire 1 + hasLowerRequest $end
   $upscope $end
  $upscope $end
 $upscope $end
$enddefinitions $end


#0
b000 #
b00 $
b00 %
0&
0'
0(
0)
0*
0+
0,
1-
b0000 .
b0001 /
00
01
02
03
04
05
06
b000 7
b00 8
#1
1,
#2
0,
#3
1,
#4
0,
#5
1,
#6
0,
#7
1,
#8
0,
#9
1,
#10
0,
0-
#11
1,
#12
0,
#13
1,
#14
0,
#15
1,
#16
0,
b1000 .
#17
1)
1,
#18
0,
#19
b001 #
b11 %
1*
1,
13
b001 7
#20
0,
#21
1,
#22
0,
b0000 .
#23
1,
#24
0,
#25
1,
#26
0,
b1000 /
#27
b11 $
1,
b11 8
#28
0,
#29
b011 #
0)
0*
1,
03
15
b011 7
#30
0,
#31
1,
#32
0,
10
#33
b100 #
1,
b100 7
